CodemaoEDUTools/__init__.py
CodemaoEDUTools/__main__.py
CodemaoEDUTools/api.py
CodemaoEDUTools/cli.py
CodemaoEDUTools/edu.py
CodemaoEDUTools/user.py
CodemaoEDUTools/work.py
codemaoedutools-2.1.6.dist-info/licenses/LICENSE
codemaoedutools-2.1.6.dist-info/METADATA
codemaoedutools-2.1.6.dist-info/WHEEL
codemaoedutools-2.1.6.dist-info/entry_points.txt
codemaoedutools-2.1.6.dist-info/top_level.txt
codemaoedutools-2.1.6.dist-info/RECORD
