Metadata-Version: 2.4
Name: codemaoedutools
Version: 2.1.6
Summary: 为编程猫社区的"老师"们提供更便捷的API调用方案，且用且珍惜
License-Expression: MIT
Requires-Python: >=3.10
License-File: LICENSE
Requires-Dist: build>=1.4.0
Requires-Dist: coloredlogs>=15.0
Requires-Dist: fake-useragent>0.1.11
Requires-Dist: openpyxl>=3.0.9
Requires-Dist: packaging>=23.1
Requires-Dist: pandas>=1.3.0
Requires-Dist: requests>=2.25.1
Requires-Dist: twine>=6.2.0
Dynamic: license-file
